PyTOMLCrypt/PyTOMLCrypt.py
PyTOMLCrypt/__init__.py
PyTOMLCrypt-2024.5.8.dist-info/LICENSE
PyTOMLCrypt-2024.5.8.dist-info/METADATA
PyTOMLCrypt-2024.5.8.dist-info/WHEEL
PyTOMLCrypt-2024.5.8.dist-info/top_level.txt
PyTOMLCrypt-2024.5.8.dist-info/RECORD
